{
  "schemaVersion": 1,
  "id": "chococraft",
  "version": "${version}",
  "name": "Chococraft 4",
  "description": "Chocobos in Minecraft\n Thanks to EddieV for the original Chococraft, ArnoSaxena(Torojimas) and clienthax for maintaining it",
  "authors": [
    "Mrbysco",
    "Xalcon",
    "Slayer5934",
    "balika011"
  ],
  "contributors": [
    "Kraehe"
  ],
  "contact": {
    "homepage": "https://www.curseforge.com/minecraft/mc-mods/chococraft",
    "sources": "https://github.com/Mrbysco/ChocoCraft4",
    "issues": "https://github.com/Mrbysco/ChocoCraft4/issues"
  },
  "license": "MIT",
  "icon": "assets/chococraft/icon.png",
  "environment": "*",
  "entrypoints": {
    "main": [
      "net.chococraft.fabric.ChococraftFabric"
    ],
    "client": [
      "net.chococraft.fabric.ChococraftClientFabric"
    ],
    "modmenu": [
      "net.chococraft.fabric.common.config.ChococraftMenuIntegration"
    ]
  },
  "mixins": [
    "chococraft.mixins.json"
  ],
  "depends": {
    "fabricloader": ">=0.15.3",
    "minecraft": "~1.20.4",
    "java": ">=17",
    "fabric-api": "*",
    "cloth-config": ">=13",
    "architectury": ">=11.1.13"
  }
}